valer.sync-1.0.1rc13-nspkg.pth
senaite/sync/__init__.py
senaite/sync/config.py
senaite/sync/configure.zcml
senaite/sync/fetchstep.py
senaite/sync/fieldmanagers.py
senaite/sync/importstep.py
senaite/sync/setuphandlers.py
senaite/sync/souphandler.py
senaite/sync/syncerror.py
senaite/sync/syncstep.py
senaite/sync/updatestep.py
senaite/sync/utils.py
senaite/sync/browser/__init__.py
senaite/sync/browser/add.py
senaite/sync/browser/autosync.py
senaite/sync/browser/configure.zcml
senaite/sync/browser/interfaces.py
senaite/sync/browser/views.py
senaite/sync/browser/templates/add.pt
senaite/sync/browser/templates/content_types.pt
senaite/sync/browser/templates/sync.pt
senaite/sync/profiles/default/actions.xml
senaite/sync/profiles/default/metadata.xml
senaite/sync/profiles/default/senaite.sync.txt
senaite/sync/upgrade/__init__.py
senaite/sync/upgrade/configure.zcml
senaite/sync/upgrade/v01_00_000.py
senaite/sync/upgrade/v01_00_001.py
valer.sync-1.0.1rc13.dist-info/DESCRIPTION.rst
valer.sync-1.0.1rc13.dist-info/METADATA
valer.sync-1.0.1rc13.dist-info/RECORD
valer.sync-1.0.1rc13.dist-info/WHEEL
valer.sync-1.0.1rc13.dist-info/entry_points.txt
valer.sync-1.0.1rc13.dist-info/metadata.json
valer.sync-1.0.1rc13.dist-info/namespace_packages.txt
valer.sync-1.0.1rc13.dist-info/top_level.txt
