Metadata-Version: 2.0
Name: valer.sync
Version: 1.0.1rc13
Summary: VALER SYNC
Home-page: https://github.com/valeriozhang/senaite.sync
Author: Valer Group LLC
Author-email: valerio.zhang@valer.us
License: GPLv3
Platform: UNKNOWN
Classifier: Programming Language :: Python
Classifier: Framework :: Plone
Classifier: Framework :: Zope2
Provides-Extra: test
Requires-Dist: plone.api
Requires-Dist: requests
Requires-Dist: setuptools
Requires-Dist: souper
Requires-Dist: valer.api (>=1.2.3rc12)
Requires-Dist: valer.jsonapi (>=1.2.3rc11)
Provides-Extra: test
Requires-Dist: Products.PloneTestCase; extra == 'test'
Requires-Dist: Products.SecureMailHost; extra == 'test'
Requires-Dist: plone.app.testing; extra == 'test'
Requires-Dist: robotsuite; extra == 'test'
Requires-Dist: unittest2; extra == 'test'
